gaea_tracker/__init__.py
gaea_tracker/aim_tracker.py
gaea_tracker/experiment_tracker.py
gaea_tracker/mlflow_tracker.py
gaea_tracker-1.2.0.12.dist-info/METADATA
gaea_tracker-1.2.0.12.dist-info/WHEEL
gaea_tracker-1.2.0.12.dist-info/top_level.txt
gaea_tracker-1.2.0.12.dist-info/RECORD
