Metadata-Version: 2.1
Name: gaea-tracker
Version: 1.2.0.12
Summary: A common tracker library.
Home-page: https://console.cloud.baidu-int.com/devops/icode/repos/baidu/mlops/gaea-operator/tree/master
Author: liuyawen03
Author-email: liuyawen03@baidu.com
License: MIT
Classifier: Programming Language :: Python
Classifier: Programming Language :: Python :: 3
Classifier: Programming Language :: Python :: 3.7
Classifier: Programming Language :: Python :: 3.8
Classifier: Programming Language :: Python :: 3.9
Requires-Python: >=3.8
Requires-Dist: windmill-train
Requires-Dist: aim (==3.17.5)
Requires-Dist: bcelogger
